reader.v
module reader (
    input clk,
    input reset,
    input [7:0] braille_out,      // Input data from braille_converter (8-bit)
    input [7:0] braille_size,     // Size of the data to be loaded (max 256)
    input braille_valid,          // Signal indicating data is valid
    input next,                   // Signal to load the next set of data
 
    output reg [7:0] reader1_out, // Reader 1 output (8-bit)
    output reg [7:0] reader2_out,
    output reg [7:0] reader3_out,
    output reg [7:0] reader4_out
);

    // States of the state machine
    parameter IDLE = 3'b000,
              LOADING = 3'b001,
              START_SIGNAL = 3'b010,
              SENDING = 3'b011,
              WAIT_NEXT = 3'b100,
              END_SIGNAL = 3'b101;

    reg [2:0] state, next_state;

    reg [7:0] buffer [0:255];       // Buffer to store up to 256 characters (8-bit)
    reg [7:0] buffer_index;         // Index to track buffer writing (8-bit to cover 256 entries)
    reg [7:0] read_addr;            // Read address for the current set of 4 characters
    reg [7:0] loaded_braille_size;  // Size of the loaded data (8-bit for up to 256 entries)

    reg next_prev;                  // Register to store previous state of 'next'
    reg next_sync;                  // Synchronized version of 'next'

    integer i;

    // Edge detection: detect falling edge of 'next'
    always @(posedge clk or negedge reset) begin
        if (!reset) begin
            next_prev <= 0;
            next_sync <= 0;
        end else begin
            next_prev <= next_sync;
            next_sync <= next;
        end
    end

    wire next_falling_edge = next_prev & ~next_sync;

    // State transition logic
    always @(posedge clk or negedge reset) begin
        if (!reset) begin
            state <= IDLE;
        end else begin
            state <= next_state;
        end
    end

    // Next state logic
    always @(*) begin
        case (state)
            IDLE: begin
                if (braille_valid) begin
                    next_state = LOADING;
                end else begin
                    next_state = IDLE;
                end
            end
            LOADING: begin
                if (buffer_index < braille_size) begin
                    next_state = LOADING;
                end else begin
                    next_state = START_SIGNAL;  // Transition to START_SIGNAL after loading is done
                end
            end
            START_SIGNAL: begin
                next_state = SENDING;  // Move to SENDING state after displaying start signal
            end
            SENDING: begin
                if (next_falling_edge && read_addr < loaded_braille_size) begin
                    if (read_addr + 4 >= loaded_braille_size) begin
                        next_state = WAIT_NEXT;  // Move to WAIT_NEXT state if last set is reached
                    end else begin
                        next_state = SENDING;
                    end
                end else begin
                    next_state = SENDING;
                end
            end
            WAIT_NEXT: begin
                if (next_falling_edge) begin
                    next_state = END_SIGNAL;  // Transition to END_SIGNAL when next is pressed again
                end else begin
                    next_state = WAIT_NEXT;  // Stay in WAIT_NEXT until next is pressed
                end
            end
            END_SIGNAL: begin
                next_state = IDLE;  // Return to IDLE state after END_SIGNAL
            end
            default: next_state = IDLE;
        endcase
    end

    // Sequential logic for loading data and sending data
    always @(posedge clk or negedge reset) begin
        if (!reset) begin
            // Reset all variables
            buffer_index <= 0;
            read_addr <= 0;
            loaded_braille_size <= 0;
            for (i = 0; i < 256; i = i + 1) begin
                buffer[i] <= 8'b00000000;
            end
            reader1_out <= 0;
            reader2_out <= 0;
            reader3_out <= 0;
            reader4_out <= 0;
        end else begin
            case (state)
                IDLE: begin
                    if (braille_valid) begin
                        buffer_index <= 0;
                        read_addr <= 0;
                        loaded_braille_size <= braille_size;
                    end
                end
                LOADING: begin
                    if (braille_valid && buffer_index < braille_size) begin
                        buffer[buffer_index] <= braille_out;
                        buffer_index <= buffer_index + 1;
                    end
                end
                START_SIGNAL: begin
                    // Display start signal (00010111b, 17h) on all outputs
                    reader1_out <= 8'b00010111;
                    reader2_out <= 8'b00010111;
                    reader3_out <= 8'b00010111;
                    reader4_out <= 8'b00010111;
                end
                SENDING: begin
                    if (next_falling_edge && read_addr < loaded_braille_size) begin
                        // Output the current set of 4 characters
                        reader1_out <= buffer[read_addr];
                        reader2_out <= buffer[read_addr + 1];
                        reader3_out <= buffer[read_addr + 2];
                        reader4_out <= buffer[read_addr + 3];
                        // Move to the next set of 4 characters
                        read_addr <= read_addr + 4;
                    end
                end
                WAIT_NEXT: begin
                    // Keep the last set of data outputs or set an end signal here if desired
                end
                END_SIGNAL: begin
                    // Display 4 sets of '00000001'
                    reader1_out <= 8'b00000001;
                    reader2_out <= 8'b00000001;
                    reader3_out <= 8'b00000001;
                    reader4_out <= 8'b00000001;
                end
            endcase
        end
    end

endmodule

mem.v
module memory(
    input [7:0] mem_addr,        // 8-bit address to support 256 words, coming from size_calculator
    output reg [7:0] mem_dout    // Output data to size_calculator & braille_converter
);

// Memory array with 256 words, each 8 bits wide
reg [7:0] memory [0:255];

// Initialize memory, synthesizable in FPGA but not in ASIC
initial begin
    $readmemh("input.txt", memory); // Read data from a hex file into memory
end

// Memory read operation
always @(*) begin
    mem_dout = memory[mem_addr];  // Read data from memory
end

endmodule

src/converter/con.v
module braille_converter (
    input clk,                    // System clock
    input reset,                  // System reset
    input [7:0] mem_dout,         // Memory data input (ASCII characters)
    output reg [7:0] braille_out, // 6-bit Braille code output
    output reg braille_valid,     // Data valid signal
    output reg [7:0] mem_addr,    // Memory address for reading data
    output reg [7:0] braille_size // size of output braille code
);

// Internal registers and counters
reg [7:0] ascii_size;              // Size of the data to convert
reg [7:0] current_ascii_size;      // Internal register to track size calculation
reg [7:0] current_braille_size;
reg indi;                    // Indicator for capital letters/digits
reg size_done;               // Flag to indicate size calculation is complete

// Braille conversion function (abbreviated)
function [7:0] ascii_to_braille;
    input [7:0] ascii;
    begin
        case (ascii)
            8'd65: ascii_to_braille = 8'b00100000; // A -> 0x20
            8'd66: ascii_to_braille = 8'b00101000; // B -> 0x28
            8'd67: ascii_to_braille = 8'b00110000; // C -> 0x30
            8'd68: ascii_to_braille = 8'b00110100; // D -> 0x34
            8'd69: ascii_to_braille = 8'b00100100; // E -> 0x24
            8'd70: ascii_to_braille = 8'b00111000; // F -> 0x38
            8'd71: ascii_to_braille = 8'b00111100; // G -> 0x3C
            8'd72: ascii_to_braille = 8'b00101100; // H -> 0x2C
            8'd73: ascii_to_braille = 8'b00011000; // I -> 0x18
            8'd74: ascii_to_braille = 8'b00011100; // J -> 0x1C
            8'd75: ascii_to_braille = 8'b00100010; // K -> 0x22
            8'd76: ascii_to_braille = 8'b00101010; // L -> 0x2A
            8'd77: ascii_to_braille = 8'b00110010; // M -> 0x32
            8'd78: ascii_to_braille = 8'b00110110; // N -> 0x36
            8'd79: ascii_to_braille = 8'b00100110; // O -> 0x26
            8'd80: ascii_to_braille = 8'b00111010; // P -> 0x3A
            8'd81: ascii_to_braille = 8'b00111110; // Q -> 0x3E
            8'd82: ascii_to_braille = 8'b00101110; // R -> 0x2E
            8'd83: ascii_to_braille = 8'b00011010; // S -> 0x1A
            8'd84: ascii_to_braille = 8'b00011110; // T -> 0x1E
            8'd85: ascii_to_braille = 8'b00100011; // U -> 0x23
            8'd86: ascii_to_braille = 8'b00101011; // V -> 0x2B
            8'd87: ascii_to_braille = 8'b00011101; // W -> 0x1D
            8'd88: ascii_to_braille = 8'b00110011; // X -> 0x33
            8'd89: ascii_to_braille = 8'b00110111; // Y -> 0x37
            8'd90: ascii_to_braille = 8'b00100111; // Z -> 0x27

            // Mapping for lowercase letters a-z
            8'd97: ascii_to_braille = 8'b00100000; // a -> 0x20
            8'd98: ascii_to_braille = 8'b00101000; // b -> 0x28
            8'd99: ascii_to_braille = 8'b00110000; // c -> 0x30
            8'd100: ascii_to_braille = 8'b00110100; // d -> 0x34
            8'd101: ascii_to_braille = 8'b00100100; // e -> 0x24
            8'd102: ascii_to_braille = 8'b00111000; // f -> 0x38
            8'd103: ascii_to_braille = 8'b00111100; // g -> 0x3C
            8'd104: ascii_to_braille = 8'b00101100; // h -> 0x2C
            8'd105: ascii_to_braille = 8'b00011000; // i -> 0x18
            8'd106: ascii_to_braille = 8'b00011100; // j -> 0x1C
            8'd107: ascii_to_braille = 8'b00100010; // k -> 0x22
            8'd108: ascii_to_braille = 8'b00101010; // l -> 0x2A
            8'd109: ascii_to_braille = 8'b00110010; // m -> 0x32
            8'd110: ascii_to_braille = 8'b00110110; // n -> 0x36
            8'd111: ascii_to_braille = 8'b00100110; // o -> 0x26
            8'd112: ascii_to_braille = 8'b00111010; // p -> 0x3A
            8'd113: ascii_to_braille = 8'b00111110; // q -> 0x3E
            8'd114: ascii_to_braille = 8'b00101110; // r -> 0x2E
            8'd115: ascii_to_braille = 8'b00011010; // s -> 0x1A
            8'd116: ascii_to_braille = 8'b00011110; // t -> 0x1E
            8'd117: ascii_to_braille = 8'b00100011; // u -> 0x23
            8'd118: ascii_to_braille = 8'b00101011; // v -> 0x2B
            8'd119: ascii_to_braille = 8'b00011101; // w -> 0x1D
            8'd120: ascii_to_braille = 8'b00110011; // x -> 0x33
            8'd121: ascii_to_braille = 8'b00110111; // y -> 0x37
            8'd122: ascii_to_braille = 8'b00100111; // z -> 0x27

            // Mapping for digits 0-9
            8'd48: ascii_to_braille = 8'b00001111; // 0 -> 0x0F
            8'd49: ascii_to_braille = 8'b00100000; // 1 -> 0x20
            8'd50: ascii_to_braille = 8'b00101000; // 2 -> 0x28
            8'd51: ascii_to_braille = 8'b00110000; // 3 -> 0x30
            8'd52: ascii_to_braille = 8'b00110100; // 4 -> 0x34
            8'd53: ascii_to_braille = 8'b00100100; // 5 -> 0x24
            8'd54: ascii_to_braille = 8'b00111000; // 6 -> 0x38
            8'd55: ascii_to_braille = 8'b00111100; // 7 -> 0x3C
            8'd56: ascii_to_braille = 8'b00101100; // 8 -> 0x2C
            8'd57: ascii_to_braille = 8'b00011000; // 9 -> 0x18

            // Mapping for common punctuation marks
            8'd32: ascii_to_braille = 8'b00000000; // Space -> 0x00
            8'd33: ascii_to_braille = 8'b00001110; // ! -> 0x0E
            8'd34: ascii_to_braille = 8'b00001010; // " -> 0x0A
            8'd35: ascii_to_braille = 8'b00010111; // # -> 0x2F
            8'd36: ascii_to_braille = 8'b00111001; // $ -> 0x39
            8'd37: ascii_to_braille = 8'b00110101; // % -> 0x35
            8'd38: ascii_to_braille = 8'b00101101; // & -> 0x2D
            8'd39: ascii_to_braille = 8'b00001000; // ' -> 0x08
            8'd40: ascii_to_braille = 8'b00011011; // ( -> 0x1B
            8'd41: ascii_to_braille = 8'b00011111; // ) -> 0x1F
            8'd42: ascii_to_braille = 8'b00100101; // * -> 0x25
            8'd43: ascii_to_braille = 8'b00010110; // + -> 0x16
            8'd44: ascii_to_braille = 8'b00000010; // , -> 0x02
            8'd45: ascii_to_braille = 8'b00001001; // - -> 0x09
            8'd46: ascii_to_braille = 8'b00000011; // . -> 0x03
            8'd47: ascii_to_braille = 8'b00010011; // / -> 0x13
            8'd58: ascii_to_braille = 8'b00010010; // : -> 0x12
            8'd59: ascii_to_braille = 8'b00011010; // ; -> 0x1A
            8'd60: ascii_to_braille = 8'b00010001; // < -> 0x
            default: ascii_to_braille = 8'b00000000; // Default (space)
        endcase
    end
endfunction

always @(posedge clk or negedge reset) begin
    if (!reset) begin
        // Resetting the internal variables
        mem_addr <= 0;
        current_ascii_size <= 0;
        ascii_size <= 0;
	current_braille_size <= 0;
	braille_size <= 0;
        braille_valid <= 0;
        size_done <= 0;
        indi <= 0;
	braille_out <= 0;
    end else begin
        if (!size_done) begin
            // Size calculation phase
            if (mem_dout == 8'd0 || mem_addr == 8'd255) begin
                // Finalize size when a zero character is detected
                ascii_size <= current_ascii_size;
	        braille_size <= current_braille_size;
                size_done <= 1;
	        braille_valid <= 1;
                mem_addr <= 0; // Reset mem_addr for the conversion phase
            end else begin
                // Accumulate size based on the type of character
                if (mem_dout >= 8'd65 && mem_dout <= 8'd90 || // Capital letters
                    mem_dout >= 8'd48 && mem_dout <= 8'd57) begin // Digits
                    //current_ascii_size <= current_ascii_size + 1;
	            current_braille_size <= current_braille_size + 2;
                end else begin
                    //current_ascii_size <= current_ascii_size + 1; // Lowercase or other characters
	            current_braille_size <= current_braille_size + 1;
                end
	            current_ascii_size <= current_ascii_size + 1;
                    mem_addr <= mem_addr + 1;
            end
        end else begin
            // Braille conversion phase
            braille_valid <= 0; // Reset valid signal at each clock cycle
            
            if (mem_addr < ascii_size) begin
                if (indi == 1) begin
                    // Output Braille for the current character (A-Z, 0-9)
                    braille_out <= ascii_to_braille(mem_dout);
                    mem_addr <= mem_addr + 1;
                    braille_valid <= 1;
                    indi <= 0;
                end else if (mem_dout >= 65 && mem_dout <= 90) begin
                    // Capital letter (A-Z) indicator
                    braille_out <= 8'b00000001;
                    braille_valid <= 1;
                    indi <= 1;
                end else if (mem_dout >= 48 && mem_dout <= 57) begin
                    // Digit (0-9) indicator
                    braille_out <= 8'b00010111;
                    braille_valid <= 1;
                    indi <= 1;
                end else begin
                    // Output Braille for the current character
                    braille_out <= ascii_to_braille(mem_dout);
                    mem_addr <= mem_addr + 1;
                    braille_valid <= 1;
                end
	    end
	    else begin
		    braille_out <= 0;
		    mem_addr <= mem_addr;
	    end
        end
    end
end

endmodule

top.v
module braille_converter_top (
    input wire clk,
    input wire reset,
    input wire next,

    output wire [7:0] reader1_out,
    output wire [7:0] reader2_out,
    output wire [7:0] reader3_out,
    output wire [7:0] reader4_out
);

    wire [7:0] mem_dout;
    wire [7:0] mem_addr;
    wire [7:0] braille_size;
    wire [7:0] braille_out;
    wire braille_valid;

    // Instantiate the Braille Converter
    braille_converter cvt (
        .clk(clk),
        .reset(reset),
        .mem_dout(mem_dout),

	    .mem_addr(mem_addr),
        .braille_out(braille_out),
	    .braille_size(braille_size),
	    .braille_valid(braille_valid)
    );

    // Instantiate the Memory Module
    memory mem (
        .mem_addr(mem_addr),

        .mem_dout(mem_dout)
    );

    // Instantiate the Reader Module
    reader rdr (
        .clk(clk),
        .reset(reset),
        .braille_out(braille_out),
        .braille_size(braille_size),
        .braille_valid(braille_valid),
        .next(next),

        .reader1_out(reader1_out),
        .reader2_out(reader2_out),
        .reader3_out(reader3_out),
        .reader4_out(reader4_out)
    );

endmodule

src/top/top_tb.v
module tb_braille_converter_top;

    // Inputs
    reg clk;
    reg reset;
    reg next;
    
    // Outputs
    wire [7:0] reader1_out;
    wire [7:0] reader2_out;
    wire [7:0] reader3_out;
    wire [7:0] reader4_out;
    
    // Instantiate the top module
    braille_converter_top top (
        .clk(clk),
        .reset(reset),
	    .next(next),

	    .reader1_out(reader1_out),
        .reader2_out(reader2_out),
        .reader3_out(reader3_out),
        .reader4_out(reader4_out)
    );
    
    // Clock Generation
    initial begin
        clk = 0;
        forever #5 clk = ~clk; // 10 time units period
    end
    
    // Test Sequence
    initial begin
        // Dump waveform data for simulation
        $dumpfile("top_tb.vcd");
        $dumpvars();
        
        // Initialize Inputs
        reset = 1;
	next = 0;
        
        // Wait for global reset
        #10;
        reset = 0;  // Reset the system
        #10;
        reset = 1;  // Release the reset
        
        // Wait for the converter to finish processing
        #355;

	next = 1;
	#10;
	next = 0;
	#20;

	next = 1;
	#100;
	next = 0;
	#20;

	next = 1;
    #200;
    next = 0;
    #20;

    next = 1;
    #200;
    next = 0;
    #20;

    next = 1;
    #200;
    next = 0;
    

	#200;

    // Finish the simulation
    $finish;
    end
    
endmodule

top_tb.vcd
$date
	Sun Aug 18 02:06:32 2024
$end
$version
	Icarus Verilog
$end
$timescale
	1s
$end
$scope module tb_braille_converter_top $end
$var wire 8 ! reader4_out [7:0] $end
$var wire 8 " reader3_out [7:0] $end
$var wire 8 # reader2_out [7:0] $end
$var wire 8 $ reader1_out [7:0] $end
$var reg 1 % clk $end
$var reg 1 & next $end
$var reg 1 ' reset $end
$scope module top $end
$var wire 1 % clk $end
$var wire 1 & next $end
$var wire 1 ' reset $end
$var wire 8 ( reader4_out [7:0] $end
$var wire 8 ) reader3_out [7:0] $end
$var wire 8 * reader2_out [7:0] $end
$var wire 8 + reader1_out [7:0] $end
$var wire 8 , mem_dout [7:0] $end
$var wire 8 - mem_addr [7:0] $end
$var wire 1 . braille_valid $end
$var wire 8 / braille_size [7:0] $end
$var wire 8 0 braille_out [7:0] $end
$scope module cvt $end
$var wire 1 % clk $end
$var wire 1 ' reset $end
$var wire 8 1 mem_dout [7:0] $end
$var reg 8 2 ascii_size [7:0] $end
$var reg 8 3 braille_out [7:0] $end
$var reg 8 4 braille_size [7:0] $end
$var reg 1 . braille_valid $end
$var reg 8 5 current_ascii_size [7:0] $end
$var reg 8 6 current_braille_size [7:0] $end
$var reg 1 7 indi $end
$var reg 8 8 mem_addr [7:0] $end
$var reg 1 9 size_done $end
$scope function ascii_to_braille $end
$var reg 8 : ascii [7:0] $end
$upscope $end
$upscope $end
$scope module mem $end
$var wire 8 ; mem_addr [7:0] $end
$var reg 8 < mem_dout [7:0] $end
$upscope $end
$scope module rdr $end
$var wire 8 = braille_out [7:0] $end
$var wire 8 > braille_size [7:0] $end
$var wire 1 . braille_valid $end
$var wire 1 % clk $end
$var wire 1 & next $end
$var wire 1 ? next_falling_edge $end
$var wire 1 ' reset $end
$var parameter 3 @ END_SIGNAL $end
$var parameter 3 A IDLE $end
$var parameter 3 B LOADING $end
$var parameter 3 C SENDING $end
$var parameter 3 D START_SIGNAL $end
$var parameter 3 E WAIT_NEXT $end
$var reg 8 F buffer_index [7:0] $end
$var reg 8 G loaded_braille_size [7:0] $end
$var reg 1 H next_prev $end
$var reg 3 I next_state [2:0] $end
$var reg 1 J next_sync $end
$var reg 8 K read_addr [7:0] $end
$var reg 8 L reader1_out [7:0] $end
$var reg 8 M reader2_out [7:0] $end
$var reg 8 N reader3_out [7:0] $end
$var reg 8 O reader4_out [7:0] $end
$var reg 3 P state [2:0] $end
$var integer 32 Q i [31:0] $end
$upscope $end
$upscope $end
$upscope $end
$enddefinitions $end
$comment Show the parameter values. $end
$dumpall
b100 E
b10 D
b11 C
b1 B
b0 A
b101 @
$end
#0
$dumpvars
bx Q
bx P
bx O
bx N
bx M
bx L
bx K
xJ
bx I
xH
bx G
bx F
x?
bx >
bx =
bx <
bx ;
bx :
x9
bx 8
x7
bx 6
bx 5
bx 4
bx 3
bx 2
bx 1
bx 0
bx /
x.
bx -
bx ,
bx +
bx *
bx )
bx (
1'
0&
0%
bx $
bx #
bx "
bx !
$end
#5
b0 I
b0 0
b0 3
b0 =
0.
0J
1%
#10
0?
b1000011 ,
b1000011 1
b1000011 <
b0 !
b0 (
b0 O
b0 "
b0 )
b0 N
b0 #
b0 *
b0 M
b0 $
b0 +
b0 L
b0 G
b0 K
b0 F
b0 P
0H
07
09
b0 /
b0 4
b0 >
b0 6
b0 2
b0 5
b0 -
b0 8
b0 ;
b100000000 Q
0%
0'
#15
b100000000 Q
1%
#20
0%
1'
#25
b1100001 ,
b1100001 1
b1100001 <
b1 -
b1 8
b1 ;
b1 5
b10 6
1%
#30
0%
#35
b1110100 ,
b1110100 1
b1110100 <
b10 -
b10 8
b10 ;
b10 5
b11 6
1%
#40
0%
#45
b1010100 ,
b1010100 1
b1010100 <
b11 -
b11 8
b11 ;
b11 5
b100 6
1%
#50
0%
#55
b1101111 ,
b1101111 1
b1101111 <
b100 -
b100 8
b100 ;
b100 5
b110 6
1%
#60
0%
#65
b1101101 ,
b1101101 1
b1101101 <
b101 -
b101 8
b101 ;
b101 5
b111 6
1%
#70
0%
#75
b1101100 ,
b1101100 1
b1101100 <
b110 -
b110 8
b110 ;
b110 5
b1000 6
1%
#80
0%
#85
b1101001 ,
b1101001 1
b1101001 <
b111 -
b111 8
b111 ;
b111 5
b1001 6
1%
#90
0%
#95
b1101111 ,
b1101111 1
b1101111 <
b1000 -
b1000 8
b1000 ;
b1000 5
b1010 6
1%
#100
0%
#105
b1101110 ,
b1101110 1
b1101110 <
b1001 -
b1001 8
b1001 ;
b1001 5
b1011 6
1%
#110
0%
#115
b1101011 ,
b1101011 1
b1101011 <
b1010 -
b1010 8
b1010 ;
b1010 5
b1100 6
1%
#120
0%
#125
b1101001 ,
b1101001 1
b1101001 <
b1011 -
b1011 8
b1011 ;
b1011 5
b1101 6
1%
#130
0%
#135
b1101110 ,
b1101110 1
b1101110 <
b1100 -
b1100 8
b1100 ;
b1100 5
b1110 6
1%
#140
0%
#145
b1100111 ,
b1100111 1
b1100111 <
b1101 -
b1101 8
b1101 ;
b1101 5
b1111 6
1%
#150
0%
#155
b0 ,
b0 1
b0 <
b1110 -
b1110 8
b1110 ;
b1110 5
b10000 6
1%
#160
0%
#165
b1000011 ,
b1000011 1
b1000011 <
b1 I
b0 -
b0 8
b0 ;
1.
19
b10000 /
b10000 4
b10000 >
b1110 2
1%
#170
0%
#175
17
b1 0
b1 3
b1 =
1.
b1 P
b10000 G
1%
#180
0%
#185
b1100001 ,
b1100001 1
b1100001 <
b1 F
07
b1 -
b1 8
b1 ;
b110000 0
b110000 3
b110000 =
1.
b1000011 :
1%
#190
0%
#195
b1110100 ,
b1110100 1
b1110100 <
b10 -
b10 8
b10 ;
b100000 0
b100000 3
b100000 =
1.
b10 F
b1100001 :
1%
#200
0%
#205
b1010100 ,
b1010100 1
b1010100 <
b11 F
b11 -
b11 8
b11 ;
b11110 0
b11110 3
b11110 =
1.
b1110100 :
1%
#210
0%
#215
17
b1 0
b1 3
b1 =
1.
b100 F
1%
#220
0%
#225
b1101111 ,
b1101111 1
b1101111 <
b101 F
07
b100 -
b100 8
b100 ;
b11110 0
b11110 3
b11110 =
1.
b1010100 :
1%
#230
0%
#235
b1101101 ,
b1101101 1
b1101101 <
b101 -
b101 8
b101 ;
b100110 0
b100110 3
b100110 =
1.
b110 F
b1101111 :
1%
#240
0%
#245
b1101100 ,
b1101100 1
b1101100 <
b111 F
b110 -
b110 8
b110 ;
b110010 0
b110010 3
b110010 =
1.
b1101101 :
1%
#250
0%
#255
b1101001 ,
b1101001 1
b1101001 <
b111 -
b111 8
b111 ;
b101010 0
b101010 3
b101010 =
1.
b1000 F
b1101100 :
1%
#260
0%
#265
b1101111 ,
b1101111 1
b1101111 <
b1001 F
b1000 -
b1000 8
b1000 ;
b11000 0
b11000 3
b11000 =
1.
b1101001 :
1%
#270
0%
#275
b1101110 ,
b1101110 1
b1101110 <
b1001 -
b1001 8
b1001 ;
b100110 0
b100110 3
b100110 =
1.
b1010 F
b1101111 :
1%
#280
0%
#285
b1101011 ,
b1101011 1
b1101011 <
b1011 F
b1010 -
b1010 8
b1010 ;
b110110 0
b110110 3
b110110 =
1.
b1101110 :
1%
#290
0%
#295
b1101001 ,
b1101001 1
b1101001 <
b1011 -
b1011 8
b1011 ;
b100010 0
b100010 3
b100010 =
1.
b1100 F
b1101011 :
1%
#300
0%
#305
b1101110 ,
b1101110 1
b1101110 <
b1101 F
b1100 -
b1100 8
b1100 ;
b11000 0
b11000 3
b11000 =
1.
b1101001 :
1%
#310
0%
#315
b1100111 ,
b1100111 1
b1100111 <
b1101 -
b1101 8
b1101 ;
b110110 0
b110110 3
b110110 =
1.
b1110 F
b1101110 :
1%
#320
0%
#325
b0 ,
b0 1
b0 <
b1111 F
b1110 -
b1110 8
b1110 ;
b111100 0
b111100 3
b111100 =
1.
b1100111 :
1%
#330
0%
#335
b10 I
b0 0
b0 3
b0 =
0.
b10000 F
1%
#340
0%
#345
b11 I
b10 P
1%
#350
0%
#355
b11 P
b10111 !
b10111 (
b10111 O
b10111 "
b10111 )
b10111 N
b10111 #
b10111 *
b10111 M
b10111 $
b10111 +
b10111 L
1%
#360
0%
#365
1%
#370
0%
#375
1J
1%
1&
#380
0%
#385
1?
0J
1H
1%
0&
#390
0%
#395
0?
0H
b100 K
b11110 !
b11110 (
b11110 O
b100000 "
b100000 )
b100000 N
b110000 #
b110000 *
b110000 M
b1 $
b1 +
b1 L
1%
#400
0%
#405
1J
1%
1&
#410
0%
#415
1H
1%
#420
0%
#425
1%
#430
0%
#435
1%
#440
0%
#445
1%
#450
0%
#455
1%
#460
0%
#465
1%
#470
0%
#475
1%
#480
0%
#485
1%
#490
0%
#495
1%
#500
0%
#505
1?
0J
1%
0&
#510
0%
#515
0?
0H
b1000 K
b110010 !
b110010 (
b110010 O
b100110 "
b100110 )
b100110 N
b11110 #
b11110 *
b11110 M
1%
#520
0%
#525
1J
1%
1&
#530
0%
#535
1H
1%
#540
0%
#545
1%
#550
0%
#555
1%
#560
0%
#565
1%
#570
0%
#575
1%
#580
0%
#585
1%
#590
0%
#595
1%
#600
0%
#605
1%
#610
0%
#615
1%
#620
0%
#625
1%
#630
0%
#635
1%
#640
0%
#645
1%
#650
0%
#655
1%
#660
0%
#665
1%
#670
0%
#675
1%
#680
0%
#685
1%
#690
0%
#695
1%
#700
0%
#705
1%
#710
0%
#715
1%
#720
0%
#725
1?
0J
1%
0&
#730
0%
#735
0?
b11 I
0H
b1100 K
b110110 !
b110110 (
b110110 O
b11000 #
b11000 *
b11000 M
b101010 $
b101010 +
b101010 L
1%
#740
0%
#745
1J
1%
1&
#750
0%
#755
1H
1%
#760
0%
#765
1%
#770
0%
#775
1%
#780
0%
#785
1%
#790
0%
#795
1%
#800
0%
#805
1%
#810
0%
#815
1%
#820
0%
#825
1%
#830
0%
#835
1%
#840
0%
#845
1%
#850
0%
#855
1%
#860
0%
#865
1%
#870
0%
#875
1%
#880
0%
#885
1%
#890
0%
#895
1%
#900
0%
#905
1%
#910
0%
#915
1%
#920
0%
#925
1%
#930
0%
#935
1%
#940
0%
#945
b100 I
1?
0J
1%
0&
#950
0%
#955
0?
b100 I
0H
b100 P
b10000 K
b111100 !
b111100 (
b111100 O
b110110 "
b110110 )
b110110 N
b100010 $
b100010 +
b100010 L
1%
#960
0%
#965
1J
1%
1&
#970
0%
#975
1H
1%
#980
0%
#985
1%
#990
0%
#995
1%
#1000
0%
#1005
1%
#1010
0%
#1015
1%
#1020
0%
#1025
1%
#1030
0%
#1035
1%
#1040
0%
#1045
1%
#1050
0%
#1055
1%
#1060
0%
#1065
1%
#1070
0%
#1075
1%
#1080
0%
#1085
1%
#1090
0%
#1095
1%
#1100
0%
#1105
1%
#1110
0%
#1115
1%
#1120
0%
#1125
1%
#1130
0%
#1135
1%
#1140
0%
#1145
1%
#1150
0%
#1155
1%
#1160
0%
#1165
b101 I
1?
0J
1%
0&
#1170
0%
#1175
0?
b0 I
0H
b101 P
1%
#1180
0%
#1185
b1 !
b1 (
b1 O
b1 "
b1 )
b1 N
b1 #
b1 *
b1 M
b1 $
b1 +
b1 L
b0 P
1%
